{"text": "Pt  is a 74 yo man with multiple medical problems  who was initially\n   admitted on [**12-9**] with MS changes, nausea and vomitting.  Was admitted\n   to the MICU  with sepsis and sent out to CC7.  Pt has had ongoing\n   hypothermia throughout admission.  He had a +RPR which is suggestive\n   for syphyllis.  On [**12-19**], he had a hypoglycemic event with BS to 38\n   treated with D5o, rsp well Then he went to IR for PICC line and LP to\n   r/o neurosyphyllis.  Only a midline was able to be placed.  Pt prone\n   during LP, then PEA arrested.  Rec'd 1 round of CPR and meds, intubated\n   and transferred to MICU for further care. Pt was hypotensive initially\n   ond was on pressors which was weaned off, successfully extubated on\n   [**11-20**]. pt contd to have tenous resp status and  had another episode of\n   mucus plug in the icu,pt was called out and sent to the floor on [**11-23**].\n   On [**11-24**] overnight pt triggered for resp distress and desaturation to\n   60\ns with questionable pleth(unable to get good pleth),received 60mg iv\n   Lasix(didn\nt putout  anything,anuric),and transferred to micu for\n   further care.\n   Pneumonia, other\n   Assessment:\n   Received pt  RR 10-30 Irreg pattern with Periods of apnea, Sats 94-100%\n   O2 FT 35%. Lungs Rhonchi dim bases, weak congested cough subglottal sx\n   for sm amts thick  blood tinge secretions.  Congested cough unable to\n   expectorate secretions.   NTx x2 for moderate amount secretion .\n   hypothermic WBC 9.9\n   Action:\n    Suctions  NT x2\n   Resp rate irreg, has [**Last Name (un) **]-[**Doctor Last Name **] pattern, periods of apnea  followed\n   by periods of tachypnea  maintains sats.  Chest PT q4hrs PT eval and\n   Pulm toilet , cont on bear hugger\n   Response:\n   Poor cough with decreased MS , temp96.6, morning temp 99.3, take off\n   bear hugger\n   Plan:\n   Pulmonary toilet\n   f/u results sputum cx\n   Need SW consult for family\n   Alteration in Nutrition\n   Assessment:\n   Cont   TF .  Abd soift nontender palpation peg inplace.  Flexiseal dr\n   [**Last Name (STitle) **] amt liq brown stool.\n   Action:\n   Rectal flexiseal cath draining brown liquid stool  + Guiac stool ,\n   indigestion food no bloody secretion form PEG and NGT. NGT d/ced\n   Response:\n   Tol TF , increased to 40cc/hr\n   Plan:\n   Resume TF adv as tol to goal.\n   Free H20 per parameters.\n   Renal failure, End stage (End stage renal disease, ESRD)\n   Assessment:\n   Anuric\n   Action:\n   Pt with foley cath in place, no u/o\n   Left arm with fistula noted to have (+)3 edema, team notified\n   Response:\n   Anuric on HD\n   Plan:\n   HD as directed Tues/thru/Sat\n   Gastrointestinal bleed, other (GI Bleed, GIB)\n   Assessment:\n   Received pt with NGT draining indigestion food no bloody secrtion cont\n   hugger.  , HCt checked, start on protonix Iv BID\n   Action:\n   cont   TF\n   Response:\n   HCT in pm 30, morning HCt 28.9\n   Plan:\n   Monitor for GIB\n   Plan EGD if rebleeds. Follow seriel Hct\n   Ineffective Coping\n   Assessment:\n   Family @ bedside all shift. Family expressed concern with difficulty\n   understanding the complication of pt recovery.\n   Action:\n   Met with MICU team to discuss Goals of care.\n   Response:\n   Family need support  to cope with pts grave state.\n   Plan:\n   [**12-27**] Palliative care  consult\n", "info": [{"num_sents": 2, "start": 43, "end": 49, "concept": "Nausea", "trigger_word": "nausea", "occ": 1, "concept_id": 0}, {"num_sents": 3, "start": 21, "end": 27, "concept": "Sepsis", "trigger_word": "sepsis", "occ": 1, "concept_id": 1}, {"num_sents": 3, "start": 21, "end": 27, "concept": "Septicemia", "trigger_word": "sepsis", "occ": 1, "concept_id": 2}, {"num_sents": 10, "start": 7, "end": 10, "concept": "Wiskott-Aldrich Syndrome", "trigger_word": "was", "occ": 1, "concept_id": 3}, {"num_sents": 19, "start": 3, "end": 12, "concept": "Pneumonia", "trigger_word": "Pneumonia", "occ": 1, "concept_id": 4}, {"num_sents": 22, "start": 39, "end": 43, "concept": "Weakness", "trigger_word": "weak", "occ": 1, "concept_id": 5}, {"num_sents": 22, "start": 54, "end": 59, "concept": "Coughing", "trigger_word": "cough", "occ": 1, "concept_id": 6}, {"num_sents": 23, "start": 57, "end": 62, "concept": "Coughing", "trigger_word": "cough", "occ": 2, "concept_id": 7}, {"num_sents": 32, "start": 8, "end": 13, "concept": "Coughing", "trigger_word": "cough", "occ": 3, "concept_id": 8}, {"num_sents": 43, "start": 40, "end": 52, "concept": "Loose stool", "trigger_word": "liquid stool", "occ": 1, "concept_id": 9}, {"num_sents": 50, "start": 54, "end": 58, "concept": "Kidney Failure", "trigger_word": "ESRD", "occ": 1, "concept_id": 10}], "row_id": 396390, "cg_id": 16818, "caregiver": {"label": "RN", "description": "RN"}, "category": "Nursing", "description": "Nursing Progress Note", "index": 132, "subject_id": 29338, "hadm_id": 127713}